{
	"info": {
		"_postman_id": "d9236485-7554-4628-a48e-b59d9bd31611",
		"name": "Pay",
		"schema": "https://schema.getpostman.com/json/collection/v2.1.0/collection.json"
	},
	"item": [
		{
			"name": "getStatus",
			"request": {
				"method": "GET",
				"header": [],
				"url": {
					"raw": "localhost:8080/status",
					"host": [
						"localhost"
					],
					"port": "8080",
					"path": [
						"status"
					]
				}
			},
			"response": []
		},
		{
			"name": "CreateOrUpdateMessage",
			"request": {
				"method": "POST",
				"header": [
					{
						"key": "Content-Type",
						"name": "Content-Type",
						"value": "application/json",
						"type": "text"
					}
				],
				"body": {
					"mode": "raw",
					"raw": "{\n\t\"id\": \"1\",\n\t\"message\": \"test message\"\n}"
				},
				"url": {
					"raw": "localhost:8080/",
					"host": [
						"localhost"
					],
					"port": "8080",
					"path": [
						""
					]
				}
			},
			"response": []
		}
	]
}